{"mean":{"confidence_interval":{"confidence_level":0.95,"lower_bound":11670996.993400002,"upper_bound":11786328.621750003},"point_estimate":11728400.586000001,"standard_error":29554.271176148486},"median":{"confidence_interval":{"confidence_level":0.95,"lower_bound":11638679.4,"upper_bound":11861415.399999999},"point_estimate":11697161.2,"standard_error":63369.64914521693},"median_abs_dev":{"confidence_interval":{"confidence_level":0.95,"lower_bound":269415.1020169258,"upper_bound":417943.4499800205},"point_estimate":360091.9542270902,"standard_error":39087.18580585005},"slope":null,"std_dev":{"confidence_interval":{"confidence_level":0.95,"lower_bound":264570.01034125703,"upper_bound":325967.3513346079},"point_estimate":297223.0125609697,"standard_error":15618.864568000647}}